equations_solver_system/__init__.py
equations_solver_system/bisection.py
equations_solver_system/cramer.py
equations_solver_system/gauss.py
equations_solver_system/gauss_jordan.py
equations_solver_system/gauss_seidel.py
equations_solver_system/jacobi.py
equations_solver_system/lu.py
equations_solver_system-0.1.2.dist-info/licenses/LICENSE
equations_solver_system-0.1.2.dist-info/METADATA
equations_solver_system-0.1.2.dist-info/WHEEL
equations_solver_system-0.1.2.dist-info/top_level.txt
equations_solver_system-0.1.2.dist-info/RECORD
