Metadata-Version: 2.4
Name: equations_solver_system
Version: 0.1.2
Summary: Librería sencilla para resolver sistemas de ecuaciones lineales y no lineales
Author: Luis Eduardo Salamanca Garcia
License: MIT
License-File: LICENSE
Dynamic: author
Dynamic: description
Dynamic: description-content-type
Dynamic: license
Dynamic: license-file
Dynamic: summary
